{"resources_index.md":"414e4698","blogs_vim.md":"79c50eb4","blogs_index.md":"31d4f7df","contact_about.md":"6c941dec","contact_index.md":"49778307","guide_emacs_gettingstarted.md":"099fe080","guide_emacs_installation.md":"66f78da1","guide_emacs_introduction.md":"b5bf3ca5","guide_emacs_resources.md":"7fb06d99","guide_emacs_index.md":"a0996295","guide_linux_installation.md":"84d97422","guide_linux_terminal.md":"b5b5c418","guide_linux_index.md":"e025b585","guide_prog-lang_rust.md":"c96d0182","guide_prog-lang_index.md":"138e1352","guide_web-dev_vue.md":"4a69b2a9","guide_web-dev_index.md":"60ca021d","guide_index.md":"1296c29a","index.md":"14d3309f"}
